GLACEON/__init__.py
GLACEON/cli.py
GLACEON/gflask.py
glaceon-1.16.0.dist-info/METADATA
glaceon-1.16.0.dist-info/WHEEL
glaceon-1.16.0.dist-info/top_level.txt
glaceon-1.16.0.dist-info/RECORD
