Metadata-Version: 2.1
Name: glaceon
Version: 1.16.0
Summary: A Simple And Clean Logging Library That Can Be Used For Any Type Of Application.
Home-page: https://pypi.python.org/pypi/glaceon
Author: Zappy
Author-email: monkey@monk.com
License: MIT
Project-URL: Homepage, https://github.com/BornPaster/Glaceon
Project-URL: Suggestions, https://github.com/BornPaster/Glaceon/issues
Platform: UNKNOWN
Classifier: Development Status :: 3 - Alpha
Classifier: Intended Audience :: Developers
Classifier: License :: OSI Approved :: MIT License
Classifier: Natural Language :: English
Classifier: Programming Language :: Python
Classifier: Programming Language :: Python :: 3
Classifier: Programming Language :: Python :: 3.7
Classifier: Programming Language :: Python :: 3.8
Classifier: Programming Language :: Python :: 3.9
Classifier: Topic :: Scientific/Engineering
Classifier: Topic :: Scientific/Engineering :: Information Analysis
Classifier: Topic :: Scientific/Engineering :: Mathematics
Classifier: Topic :: Scientific/Engineering :: Visualization
Classifier: Topic :: Software Development :: Libraries
Classifier: Topic :: Utilities
Requires-Python: ~=3.7
